MANIFEST.in
README.rst
setup.py
corlab_theme/__init__.py
corlab_theme/globaltoc.html
corlab_theme/theme.conf
corlab_theme/static/corlab.css
sphinx_corlab_theme.egg-info/PKG-INFO
sphinx_corlab_theme.egg-info/SOURCES.txt
sphinx_corlab_theme.egg-info/dependency_links.txt
sphinx_corlab_theme.egg-info/not-zip-safe
sphinx_corlab_theme.egg-info/requires.txt
sphinx_corlab_theme.egg-info/top_level.txt